fiole.py
fiole-0.4.1.dist-info/RECORD
fiole-0.4.1.dist-info/WHEEL
fiole-0.4.1.dist-info/DESCRIPTION.rst
fiole-0.4.1.dist-info/metadata.json
fiole-0.4.1.dist-info/METADATA
fiole-0.4.1.dist-info/top_level.txt
